{
  "gitSyncId": "66f2c1598714823e2c82ae8c_0a730ece-538f-43b7-96c7-ad09ae029056",
  "id": "Movie Database_updateMoviePT2",
  "pluginId": "postgres-plugin",
  "pluginType": "DB",
  "unpublishedAction": {
    "actionConfiguration": {
      "body": "UPDATE public.\"movies\"\nSET \n    original_title = '{{MoviesTable.updatedRow.original_title}}',\n    overview = '{{MoviesTable.updatedRow.overview}}',\n    popularity = COALESCE(NULLIF('{{MoviesTable.updatedRow.popularity}}', '')::double precision, popularity),\n    vote_average = COALESCE(NULLIF('{{MoviesTable.updatedRow.vote_average}}', '')::double precision, vote_average),\n    vote_count = COALESCE(NULLIF('{{MoviesTable.updatedRow.vote_count}}', '')::double precision, vote_count),\n    genres = '{{MoviesTable.updatedRow.genres}}',\n    tagline = '{{MoviesTable.updatedRow.tagline}}',\n    director = '{{MoviesTable.updatedRow.director}}',\n    keywords = '{{MoviesTable.updatedRow.keywords}}'\nWHERE id = COALESCE(NULLIF('{{MoviesTable.updatedRow.id}}', '')::integer, id);",
      "encodeParamsToggle": true,
      "paginationType": "NONE",
      "pluginSpecifiedTemplates": [
        {
          "value": true
        }
      ],
      "timeoutInMillisecond": 10000
    },
    "confirmBeforeExecute": false,
    "datasource": {
      "id": "Movies",
      "isAutoGenerated": false,
      "name": "Movies",
      "pluginId": "postgres-plugin"
    },
    "dynamicBindingPathList": [
      {
        "key": "body"
      }
    ],
    "executeOnLoad": false,
    "name": "updateMoviePT2",
    "pageId": "Movie Database",
    "userSetOnLoad": false
  }
}